oneNeuron/__init__.py
oneNeuron/perceptron.py
Perceptron_pypi_sharath957-0.0.1.dist-info/LICENSE
Perceptron_pypi_sharath957-0.0.1.dist-info/METADATA
Perceptron_pypi_sharath957-0.0.1.dist-info/WHEEL
Perceptron_pypi_sharath957-0.0.1.dist-info/top_level.txt
Perceptron_pypi_sharath957-0.0.1.dist-info/RECORD
