Metadata-Version: 2.1
Name: Perceptron-pypi-sharath957
Version: 0.0.1
Summary: It is a implementation of perceptron
Home-page: https://github.com/sharath957/Perceptron_pypi
Author: sharath957
Author-email: sharath957@gmail.com
License: UNKNOWN
Project-URL: Bug Tracker, https://github.com/sharath957/Perceptron_pypi/issues
Platform: UNKNOWN
Classifier: Programming Language :: Python :: 3
Classifier: License :: OSI Approved :: MIT License
Classifier: Operating System :: OS Independent
Requires-Python: >=3.7
License-File: LICENSE
Requires-Dist: numpy
Requires-Dist: tqdm
